pdflinkcheck_rust/LICENSE
pdflinkcheck_rust/PDFiumConfig.cmake
pdflinkcheck_rust/VERSION
pdflinkcheck_rust/__init__.py
pdflinkcheck_rust/pdflinkcheck_rust.cpython-313-darwin.so
pdflinkcheck_rust-0.1.14.dist-info/METADATA
pdflinkcheck_rust-0.1.14.dist-info/WHEEL
pdflinkcheck_rust-0.1.14.dist-info/licenses/LICENSE
pdflinkcheck_rust-0.1.14.dist-info/RECORD
