Metadata-Version: 2.4
Name: pdflinkcheck-rust
Version: 0.1.14
License-File: LICENSE
Summary: Rust core for pdflinkcheck: fast PDF link & TOC extraction
Author-email: George Clayton Bennett <george.bennett@memphistn.gov>
Requires-Python: >=3.10
